mml_tasks/__init__.py
mml_tasks/activate.py
mml_tasks/cli.py
mml_tasks/configs/__init__.py
mml_tasks/configs/tasks/all.yaml
mml_tasks/configs/tasks/all_clas.yaml
mml_tasks/configs/tasks/new.yaml
mml_tasks/creators/__init__.py
mml_tasks/creators/classification/__init__.py
mml_tasks/creators/classification/_template.py
mml_tasks/creators/classification/aptos_blindness.py
mml_tasks/creators/classification/barretts_esophagus.py
mml_tasks/creators/classification/brain_tumor.py
mml_tasks/creators/classification/brain_tumor_type.py
mml_tasks/creators/classification/breast_ultrasound.py
mml_tasks/creators/classification/caltech101.py
mml_tasks/creators/classification/caltech256.py
mml_tasks/creators/classification/cataract.py
mml_tasks/creators/classification/cervical_cancer_screening.py
mml_tasks/creators/classification/chexpert.py
mml_tasks/creators/classification/cholec45.py
mml_tasks/creators/classification/cholec80.py
mml_tasks/creators/classification/cifar.py
mml_tasks/creators/classification/covid_ct.py
mml_tasks/creators/classification/covid_ct_crawled.py
mml_tasks/creators/classification/covid_xray.py
mml_tasks/creators/classification/deep_drid.py
mml_tasks/creators/classification/derm7pt.py
mml_tasks/creators/classification/emnist.py
mml_tasks/creators/classification/hyper_kvasir.py
mml_tasks/creators/classification/ibean.py
mml_tasks/creators/classification/idle_frame_recognition.py
mml_tasks/creators/classification/isic20.py
mml_tasks/creators/classification/kvasir_capsule.py
mml_tasks/creators/classification/lapgyn4.py
mml_tasks/creators/classification/laryngeal.py
mml_tasks/creators/classification/mednode.py
mml_tasks/creators/classification/mnist.py
mml_tasks/creators/classification/mura.py
mml_tasks/creators/classification/nbi_infframes.py
mml_tasks/creators/classification/nerthus.py
mml_tasks/creators/classification/pneumonia.py
mml_tasks/creators/classification/shenzhen_tuberculosis.py
mml_tasks/creators/classification/sklin2.py
mml_tasks-0.6.0.dist-info/LICENSE.txt
mml_tasks-0.6.0.dist-info/METADATA
mml_tasks-0.6.0.dist-info/WHEEL
mml_tasks-0.6.0.dist-info/entry_points.txt
mml_tasks-0.6.0.dist-info/top_level.txt
mml_tasks-0.6.0.dist-info/RECORD
